tabsvsspaces/__init__.py
tabsvsspaces/__main__.py
tabsvsspaces/_main.py
tabsvsspaces/find_stats.py
tabsvsspaces/pathtype.py
tabsvsspaces/print_stats.py
tabsvsspaces/stats.py
tabsvsspaces-1.1.1.dist-info/METADATA
tabsvsspaces-1.1.1.dist-info/WHEEL
tabsvsspaces-1.1.1.dist-info/entry_points.txt
tabsvsspaces-1.1.1.dist-info/top_level.txt
tabsvsspaces-1.1.1.dist-info/RECORD
