Metadata-Version: 2.1
Name: tabsvsspaces
Version: 1.1.1
Summary: A tool for counting spaces vs tabs in a codebase
Home-page: https://github.com/romangraef/tabsvsspaces
Author: Roman Gräf
Author-email: romangraef@gmail.com
License: MIT
Keywords: tabs spaces linecount counting commandline
Platform: UNKNOWN
Classifier: Development Status :: 5 - Production/Stable
Classifier: Environment :: Console
Classifier: Intended Audience :: Developers
Classifier: Intended Audience :: Religion
Classifier: License :: OSI Approved :: MIT License
Classifier: Programming Language :: Python :: 3.5
Classifier: Typing :: Typed
